tv_audio_extractor/__init__.py
tv_audio_extractor/main.py
tv_audio_extractor/utils.py
tv_audio_extractor-0.1.4.dist-info/entry_points.txt
tv_audio_extractor-0.1.4.dist-info/WHEEL
tv_audio_extractor-0.1.4.dist-info/METADATA
tv_audio_extractor-0.1.4.dist-info/RECORD
